{
  "slug": "codigos-bike-league",
  "name": "Bike League",
  "thumbnail": "https://tr.rbxcdn.com/180DAY-7c7a3da75d3d5af989d818c44d7fab7a/512/512/Image/Png/noFilter",
  "description": "Todos los códigos activos para Bike League en Roblox",
  "metaTitle": "Códigos Bike League Roblox (Febrero 2026) - Códigos Gratis",
  "metaDescription": "Lista actualizada de códigos para Bike League en Roblox. 5 códigos activos. Consigue recompensas gratis.",
  "lastUpdated": "2026-02-23",
  "activeCodes": [
    {
      "code": "5KLikes",
      "reward": "Recompensas gratis"
    },
    {
      "code": "2KLIKES",
      "reward": "Recompensas gratis"
    },
    {
      "code": "100Likes",
      "reward": "2 Train pociones"
    },
    {
      "code": "Release",
      "reward": "2 Train pociones"
    },
    {
      "code": "12KLIKES",
      "reward": "Recompensas gratis"
    }
  ],
  "expiredCodes": [],
  "howToRedeem": [
    "Abre Bike League en Roblox",
    "Busca el botón de códigos en el menú",
    "Escribe el código y pulsa Canjear"
  ],
  "placeId": 86588465079478,
  "universeId": 6589947100,
  "developer": "Bike Race Champions",
  "genre": "All",
  "totalVisits": 50784397,
  "playerCount": 155,
  "favourites": 1083464
}
