{
  "slug": "codigos-race-merge-simulator",
  "name": "Race Merge Simulator",
  "thumbnail": "https://tr.rbxcdn.com/180DAY-ed97d3e46b6fe62e8e9eb0858425278a/512/512/Image/Png/noFilter",
  "description": "Todos los códigos activos para Race Merge Simulator en Roblox",
  "metaTitle": "Códigos Race Merge Simulator Roblox (Febrero 2026) - Códigos Gratis",
  "metaDescription": "Lista actualizada de códigos para Race Merge Simulator en Roblox. 4 códigos activos. Consigue recompensas gratis.",
  "lastUpdated": "2026-02-23",
  "activeCodes": [
    {
      "code": "VROOM",
      "reward": "A Boost gratis"
    },
    {
      "code": "1a22cf",
      "reward": "A Boost gratis"
    },
    {
      "code": "p0z15m",
      "reward": "A Boost gratis"
    },
    {
      "code": "RELEASE",
      "reward": "Cash"
    }
  ],
  "expiredCodes": [],
  "howToRedeem": [
    "Abre Race Merge Simulator en Roblox",
    "Busca el botón de códigos en el menú",
    "Escribe el código y pulsa Canjear"
  ],
  "placeId": 13536908241,
  "universeId": 4705426872
}
