{
  "slug": "codigos-ninja-blade",
  "name": "Ninja Blade",
  "thumbnail": "https://tr.rbxcdn.com/180DAY-fcb62be4328910d1e083b3ffb238c71e/512/512/Image/Png/noFilter",
  "description": "Todos los códigos activos para Ninja Blade en Roblox",
  "metaTitle": "Códigos Ninja Blade Roblox (Febrero 2026) - Códigos Gratis",
  "metaDescription": "Lista actualizada de códigos para Ninja Blade en Roblox. 1 códigos activos. Consigue recompensas gratis.",
  "lastUpdated": "2026-02-23",
  "activeCodes": [
    {
      "code": "ninjablade2021",
      "reward": "Sword"
    }
  ],
  "expiredCodes": [
    {
      "code": "welcometohotpot",
      "reward": "Oro monedas, Skill, and Weapon"
    },
    {
      "code": "niceto200",
      "reward": "600 oro monedas"
    },
    {
      "code": "betterthan350",
      "reward": "Skills"
    },
    {
      "code": "thxto500",
      "reward": "A Weapon"
    },
    {
      "code": "goodway",
      "reward": "An Assistive Skill"
    },
    {
      "code": "boom1000",
      "reward": "960 oro monedas"
    },
    {
      "code": "trybest",
      "reward": "15 diamantes"
    },
    {
      "code": "behappy",
      "reward": "420 oro monedas & 15 diamantes"
    },
    {
      "code": "updategift",
      "reward": "120 oro monedas"
    },
    {
      "code": "sosorry",
      "reward": "15 diamantes"
    },
    {
      "code": "letsparty",
      "reward": "A Dwarf Hammer"
    },
    {
      "code": "wealth",
      "reward": "960 oro monedas & 30 diamantes"
    },
    {
      "code": "thomasninja",
      "reward": "1,200 oro monedas & 30 diamantes"
    }
  ],
  "howToRedeem": [
    "Abre Ninja Blade en Roblox",
    "Busca el botón de códigos en el menú",
    "Escribe el código y pulsa Canjear"
  ],
  "placeId": 6734679364,
  "universeId": 2547688734,
  "developer": "Hotpot Studio",
  "genre": "All",
  "totalVisits": 9096698,
  "favourites": 21707
}
