{
  "slug": "codigos-pet-fishing-simulator",
  "name": "Pet Fishing Simulator",
  "thumbnail": "https://tr.rbxcdn.com/180DAY-b5d374c38b8eef17b7deb29e91c0f1ea/512/512/Image/Png/noFilter",
  "description": "Todos los códigos activos para Pet Fishing Simulator en Roblox",
  "metaTitle": "Códigos Pet Fishing Simulator Roblox (Febrero 2026) - Códigos Gratis",
  "metaDescription": "Lista actualizada de códigos para Pet Fishing Simulator en Roblox. 3 códigos activos. Consigue recompensas gratis.",
  "lastUpdated": "2026-02-23",
  "activeCodes": [
    {
      "code": "NEWGAME",
      "reward": "Monedas gratis"
    },
    {
      "code": "PFS500LIKE",
      "reward": "Gemas gratis"
    },
    {
      "code": "PFS1KLIKE",
      "reward": "Gemas gratis"
    }
  ],
  "expiredCodes": [],
  "howToRedeem": [
    "Abre Pet Fishing Simulator en Roblox",
    "Busca el botón de códigos en el menú",
    "Escribe el código y pulsa Canjear"
  ],
  "placeId": 10184360875,
  "universeId": 3735634697,
  "developer": "AirPenguin Simulator",
  "genre": "All",
  "totalVisits": 3987529,
  "favourites": 18795
}
