{
  "slug": "codigos-kraken-game",
  "name": "Kraken Game",
  "thumbnail": "https://tr.rbxcdn.com/180DAY-641f837fa99b5235854159a9edd347d6/512/512/Image/Png/noFilter",
  "description": "Todos los códigos activos para Kraken Game en Roblox",
  "metaTitle": "Códigos Kraken Game Roblox (Febrero 2026) - Códigos Gratis",
  "metaDescription": "Lista actualizada de códigos para Kraken Game en Roblox. 6 códigos activos. Consigue recompensas gratis.",
  "lastUpdated": "2026-02-23",
  "activeCodes": [
    {
      "code": "9KLIKES",
      "reward": "Recompensas"
    },
    {
      "code": "8KLIKES",
      "reward": "Recompensas"
    },
    {
      "code": "4KLIKES",
      "reward": "Recompensas"
    },
    {
      "code": "5KLIKES",
      "reward": "Recompensas"
    },
    {
      "code": "6KLIKES",
      "reward": "Recompensas"
    },
    {
      "code": "7KLIKES",
      "reward": "Recompensas"
    }
  ],
  "expiredCodes": [
    {
      "code": "2.5KLIKES",
      "reward": "Recompensas"
    },
    {
      "code": "1.5KLIKESTHX",
      "reward": "Recompensas"
    }
  ],
  "howToRedeem": [
    "Abre Kraken Game en Roblox",
    "Busca el botón de códigos en el menú",
    "Escribe el código y pulsa Canjear"
  ],
  "placeId": 106159203290418,
  "universeId": 7538895650,
  "developer": "DTP Trends",
  "genre": "All",
  "totalVisits": 13058029,
  "playerCount": 2,
  "favourites": 98286
}
