{
  "slug": "codigos-coruscant-roleplay",
  "name": "Coruscant Roleplay",
  "thumbnail": "https://tr.rbxcdn.com/180DAY-5fdb20f6be3f7c82f35e8e5ecf78617c/512/512/Image/Png/noFilter",
  "description": "Todos los códigos activos para Coruscant Roleplay en Roblox",
  "metaTitle": "Códigos Coruscant Roleplay Roblox (Febrero 2026) - Códigos Gratis",
  "metaDescription": "Lista actualizada de códigos para Coruscant Roleplay en Roblox. 2 códigos activos. Consigue recompensas gratis.",
  "lastUpdated": "2026-02-23",
  "activeCodes": [
    {
      "code": "JETP4CK",
      "reward": "Jetpack gratis"
    },
    {
      "code": "GARISBACK",
      "reward": "10,000 créditos"
    }
  ],
  "expiredCodes": [],
  "howToRedeem": [
    "Abre Coruscant Roleplay en Roblox",
    "Busca el botón de códigos en el menú",
    "Escribe el código y pulsa Canjear"
  ],
  "placeId": 4238077359,
  "universeId": 1383204830,
  "developer": "|GAR| Grand Army of the Republic |",
  "genre": "RPG",
  "totalVisits": 77003774,
  "playerCount": 383,
  "favourites": 415287
}
