{
  "slug": "codigos-basketball-legends",
  "name": "Basketball Legends",
  "thumbnail": "https://tr.rbxcdn.com/180DAY-43c1d15b39ebdb2b64ed231e774ff703/512/512/Image/Png/noFilter",
  "description": "Todos los códigos activos para Basketball Legends en Roblox",
  "metaTitle": "Códigos Basketball Legends (Febrero 2026) - Códigos Gratis",
  "metaDescription": "Lista actualizada de códigos para Basketball Legends en Roblox. Consigue recompensas gratis.",
  "lastUpdated": "2026-02-23",
  "activeCodes": [
    {
      "code": "500KFAVS",
      "reward": "Recompensas"
    },
    {
      "code": "TURKEY25",
      "reward": "Halloween Case"
    },
    {
      "code": "FALLDAY",
      "reward": "Exclusivo Banner"
    },
    {
      "code": "wow",
      "reward": "Halloween Case"
    },
    {
      "code": "CLANS",
      "reward": "Halloween Case"
    },
    {
      "code": "DELAYED",
      "reward": "Skin Halloween Case"
    },
    {
      "code": "UPCOMING",
      "reward": "Halloween Case"
    },
    {
      "code": "SUPERSPOOKY",
      "reward": "Halloween Case"
    },
    {
      "code": "SUPERSCARY",
      "reward": "Halloween skin Case"
    },
    {
      "code": "JAMALCHOCOLATEPUDDING",
      "reward": "UBV's Effect"
    },
    {
      "code": "JAMALBANANAPUDDING",
      "reward": "Jamal's Duck"
    },
    {
      "code": "banana",
      "reward": "1 Elite cofre"
    },
    {
      "code": "MAGICAL",
      "reward": "1 Elite cofre"
    },
    {
      "code": "SUMMER25",
      "reward": "1 Summer25 Effect cofre"
    },
    {
      "code": "DELAYCASE",
      "reward": "1 Summer25 Effect cofre"
    },
    {
      "code": "DELAYSKIN",
      "reward": "1 Summer25 skin cofre"
    },
    {
      "code": "USA2025",
      "reward": "For 10k monedas"
    },
    {
      "code": "CHAMPIONS",
      "reward": "For recompensas gratis"
    },
    {
      "code": "SPACE2",
      "reward": "Space Case #2"
    },
    {
      "code": "ELECTRIC",
      "reward": "2k monedas"
    },
    {
      "code": "300KLIKES",
      "reward": "Recompensas gratis"
    },
    {
      "code": "AURORA",
      "reward": "Aurora ball skin gratis"
    },
    {
      "code": "STPATRICKS",
      "reward": "Spring 2025 Case"
    },
    {
      "code": "SPRING2025",
      "reward": "Spring 2025 Case"
    },
    {
      "code": "VALENTINES",
      "reward": "10k monedas"
    },
    {
      "code": "280KLIKES",
      "reward": "Recompensas gratis"
    },
    {
      "code": "ANIMECASE2",
      "reward": "1x Anime Case #2"
    },
    {
      "code": "270KLIKES",
      "reward": "Recompensas gratis"
    },
    {
      "code": "260KLIKES",
      "reward": "5k monedas"
    },
    {
      "code": "2025",
      "reward": "Recompensas gratis"
    },
    {
      "code": "TYFOR100K",
      "reward": "Spring 2024 Case"
    },
    {
      "code": "XMAS24",
      "reward": "Christmas Case"
    },
    {
      "code": "SANTA24",
      "reward": "Christmas skin Case"
    },
    {
      "code": "FESTIVE24",
      "reward": "Warped Code Effect"
    },
    {
      "code": "ALMOSTXMAS",
      "reward": "Recompensas gratis"
    },
    {
      "code": "250KLIKES",
      "reward": "5k monedas"
    },
    {
      "code": "THANKSGIVING24",
      "reward": "Effect Case"
    },
    {
      "code": "240KLIKES",
      "reward": "Monedas"
    },
    {
      "code": "230KLIKES",
      "reward": "5k monedas"
    },
    {
      "code": "220KLIKES",
      "reward": "5k monedas"
    },
    {
      "code": "SPOOKY2",
      "reward": "Halloween Case"
    },
    {
      "code": "ANIMECASE",
      "reward": "Anime Case"
    },
    {
      "code": "200KLIKES",
      "reward": "15k monedas"
    },
    {
      "code": "190KLIKES",
      "reward": "5k monedas"
    },
    {
      "code": "COINBOOST",
      "reward": "Doble moneda Boost for 30 minutos"
    },
    {
      "code": "170KLIKES",
      "reward": "5k monedas"
    },
    {
      "code": "180KLIKES",
      "reward": "5k monedas"
    },
    {
      "code": "SUMMER24",
      "reward": "Summer Case"
    }
  ],
  "expiredCodes": [
    {
      "code": "BIRTHDAY",
      "reward": "1x Birthday Exalted Effect"
    },
    {
      "code": "190KLIKES",
      "reward": "5,000 monedas"
    },
    {
      "code": "180KLIKES",
      "reward": "5,000 monedas"
    },
    {
      "code": "170KLIKES",
      "reward": "5,000 monedas"
    },
    {
      "code": "SUMMER24",
      "reward": "X1 Summer Case"
    },
    {
      "code": "NEWCASE",
      "reward": "X1 Effect Case #3"
    },
    {
      "code": "DELAYLEGENDS",
      "reward": "Musical Phenomenon Effect"
    },
    {
      "code": "MEMORIALDAY24",
      "reward": "10,000 monedas"
    },
    {
      "code": "150KLIKES",
      "reward": "Recompensas gratis"
    },
    {
      "code": "160KLIKES",
      "reward": "Recompensas gratis"
    },
    {
      "code": "CYBER",
      "reward": "Recompensas gratis"
    },
    {
      "code": "GALAXY",
      "reward": "Recompensas gratis"
    },
    {
      "code": "ECLIPSE24",
      "reward": "Recompensas gratis"
    },
    {
      "code": "EASTER24",
      "reward": "Recompensas gratis"
    },
    {
      "code": "HL1KLIKES",
      "reward": "Recompensas gratis"
    },
    {
      "code": "IMLUCKYTODAY",
      "reward": "Recompensas gratis"
    },
    {
      "code": "120KLIKES",
      "reward": "Recompensas gratis"
    },
    {
      "code": "130KLIKES",
      "reward": "Recompensas gratis"
    },
    {
      "code": "IRISHSPRINGGREEN",
      "reward": "Recompensas gratis"
    },
    {
      "code": "SORRY4REBOOT",
      "reward": "Limitado time skins case gratis"
    },
    {
      "code": "100KLIKES",
      "reward": "Recompensas gratis"
    },
    {
      "code": "2024",
      "reward": "Recompensas gratis"
    },
    {
      "code": "JOLLY",
      "reward": "1X CHRISTMAS CASE"
    },
    {
      "code": "80KLIKES",
      "reward": "Recompensas gratis"
    },
    {
      "code": "BLACKFRIDAY",
      "reward": "Effect Case #1 gratis"
    },
    {
      "code": "70KLIKES",
      "reward": "Recompensas gratis"
    },
    {
      "code": "60KLIKES",
      "reward": "Recompensas gratis"
    },
    {
      "code": "friday13effects",
      "reward": "Recompensas gratis"
    },
    {
      "code": "friday13skins",
      "reward": "Recompensas gratis"
    },
    {
      "code": "friday13banners",
      "reward": "Recompensas gratis"
    },
    {
      "code": "SPOOKY",
      "reward": "Recompensas gratis"
    },
    {
      "code": "50KLIKES",
      "reward": "Recompensas gratis"
    },
    {
      "code": "40KLIKES",
      "reward": "Recompensas gratis"
    },
    {
      "code": "REWARDS",
      "reward": "Recompensas gratis"
    },
    {
      "code": "LOBCITY",
      "reward": "10,000 monedas"
    },
    {
      "code": "30KLIKES",
      "reward": "Recompensas gratis"
    },
    {
      "code": "BOOST",
      "reward": "FOR 30 MINS 2x monedas BOOSTER"
    },
    {
      "code": "20KLIKES",
      "reward": "Recompensas gratis"
    },
    {
      "code": "SKINS",
      "reward": "3 moneda skin Case #1"
    },
    {
      "code": "CHEESY",
      "reward": "Recompensas gratis"
    },
    {
      "code": "COINS",
      "reward": "10,000 monedas"
    },
    {
      "code": "10KLIKES",
      "reward": "Recompensas gratis"
    },
    {
      "code": "5KLIKES",
      "reward": "Recompensas gratis"
    },
    {
      "code": "1KLIKES",
      "reward": "Recompensas gratis"
    },
    {
      "code": "SORRY",
      "reward": "Recompensas gratis"
    },
    {
      "code": "HEARTBURST",
      "reward": "Exclusivo effect"
    },
    {
      "code": "JANUARY",
      "reward": "Recompensas gratis"
    },
    {
      "code": "ANIMEBOSSRAID",
      "reward": "Recompensas gratis"
    },
    {
      "code": "210KLIKES",
      "reward": "Monedas"
    },
    {
      "code": "TRIM",
      "reward": "Recompensas gratis"
    },
    {
      "code": "ZEGWASLATE",
      "reward": "Recompensas gratis"
    },
    {
      "code": "110KLIKES",
      "reward": "Recompensas gratis"
    },
    {
      "code": "SHAMROCKSZN",
      "reward": "Recompensas gratis"
    }
  ],
  "howToRedeem": [
    "Abre Basketball Legends en Roblox",
    "Busca el icono de códigos en el menú",
    "Escribe el código y pulsa Canjear"
  ],
  "playerCount": 9841,
  "totalVisits": 654934342,
  "likes": 476431,
  "genre": "Sports",
  "placeId": 14259168147,
  "introText": "Basketball Legends es un juego de deportes en Roblox con más de 654 millones de visitas. Juega partidos de baloncesto competitivos, mejora las habilidades de tu jugador y compite para convertirte en una leyenda de la cancha.",
  "whatAreCodes": "Los códigos de Basketball Legends te dan monedas, boosts de estadísticas y equipamiento exclusivo para potenciar el rendimiento de tu jugador.",
  "howToGetCodes": "Los desarrolladores publican nuevos códigos en Twitter/X y en su servidor de Discord, generalmente cuando se lanzan temporadas nuevas o se celebran hitos del juego."
}
